mimeogram/data/.gitignore
mimeogram/data/configuration/general.toml
mimeogram/data/pictures/logo.svg
mimeogram/data/prompts/mimeogram.md
mimeogram/__init__.py
mimeogram/__main__.py
mimeogram/acquirers.py
mimeogram/apply.py
mimeogram/cli.py
mimeogram/create.py
mimeogram/differences.py
mimeogram/display.py
mimeogram/edit.py
mimeogram/exceptions.py
mimeogram/formatters.py
mimeogram/interactions.py
mimeogram/interfaces.py
mimeogram/parsers.py
mimeogram/parts.py
mimeogram/prompt.py
mimeogram/py.typed
mimeogram/tokenizers.py
mimeogram/updaters.py
mimeogram/__/__init__.py
mimeogram/__/application.py
mimeogram/__/asyncf.py
mimeogram/__/configuration.py
mimeogram/__/dictedits.py
mimeogram/__/distribution.py
mimeogram/__/environment.py
mimeogram/__/exceptions.py
mimeogram/__/generics.py
mimeogram/__/imports.py
mimeogram/__/inscription.py
mimeogram/__/io.py
mimeogram/__/nomina.py
mimeogram/__/preparation.py
mimeogram/__/state.py
mimeogram/_typedecls/gitignorefile/__init__.pyi
mimeogram/_typedecls/icecream/__init__.pyi
mimeogram/_typedecls/icecream/builtins.pyi
mimeogram/_typedecls/icecream/icecream.pyi
mimeogram/_typedecls/pyperclip/__init__.pyi
mimeogram/fsprotect/__.py
mimeogram/fsprotect/__init__.py
mimeogram/fsprotect/cache.py
mimeogram/fsprotect/core.py
mimeogram/fsprotect/home.py
mimeogram/fsprotect/macos.py
mimeogram/fsprotect/project.py
mimeogram/fsprotect/unix.py
mimeogram/fsprotect/windows.py
mimeogram-1.5.dist-info/METADATA
mimeogram-1.5.dist-info/WHEEL
mimeogram-1.5.dist-info/entry_points.txt
mimeogram-1.5.dist-info/licenses/LICENSE.txt
mimeogram-1.5.dist-info/RECORD
