Metadata-Version: 2.4
Name: mimeogram
Version: 1.5
Summary: Exchange of file collections with LLMs.
Project-URL: Homepage, https://github.com/emcd/python-mimeogram
Project-URL: Documentation, https://emcd.github.io/python-mimeogram
Project-URL: Download, https://pypi.org/project/mimeogram/#files
Project-URL: Source Code, https://github.com/emcd/python-mimeogram
Project-URL: Issue Tracker, https://github.com/emcd/python-mimeogram/issues
Author-email: Eric McDonald <emcd@users.noreply.github.com>
License-Expression: Apache-2.0
License-File: LICENSE.txt
Keywords: ai,cli,documents,interchange,llm
Classifier: Development Status :: 4 - Beta
Classifier: Intended Audience :: Developers
Classifier: Intended Audience :: End Users/Desktop
Classifier: License :: OSI Approved :: Apache Software License
Classifier: Programming Language :: Python :: 3 :: Only
Classifier: Programming Language :: Python :: 3.10
Classifier: Programming Language :: Python :: 3.11
Classifier: Programming Language :: Python :: 3.12
Classifier: Programming Language :: Python :: 3.13
Classifier: Programming Language :: Python :: Implementation :: CPython
Classifier: Programming Language :: Python :: Implementation :: PyPy
Classifier: Topic :: Communications :: Chat
Classifier: Topic :: Scientific/Engineering :: Artificial Intelligence
Classifier: Topic :: Scientific/Engineering :: Interface Engine/Protocol Translator
Classifier: Topic :: Text Processing :: General
Requires-Python: >=3.10
Requires-Dist: absence~=1.1
Requires-Dist: accretive~=4.1
Requires-Dist: aiofiles
Requires-Dist: chardet
Requires-Dist: exceptiongroup
Requires-Dist: frigid~=4.1
Requires-Dist: gitignorefile
Requires-Dist: httpx
Requires-Dist: icecream-truck~=1.5
Requires-Dist: importlib-metadata
Requires-Dist: importlib-resources
Requires-Dist: patiencediff
Requires-Dist: platformdirs
Requires-Dist: puremagic
Requires-Dist: pyperclip
Requires-Dist: python-dotenv
Requires-Dist: readchar
Requires-Dist: rich
Requires-Dist: tiktoken
Requires-Dist: tomli
Requires-Dist: typing-extensions
Requires-Dist: tyro
Requires-Dist: wcmatch
